{
    "name": "ImageInsecte",
    "fields": [
        {
            "fieldName": "imageUrl",
            "fieldType": "String"
        }
    ],
    "relationships": [
        {
            "relationshipName": "insecte",
            "otherEntityName": "insecte",
            "relationshipType": "many-to-one",
            "otherEntityField": "id"
        }
    ],
    "changelogDate": "20190216191709",
    "entityTableName": "image_insecte",
    "dto": "mapstruct",
    "pagination": "no",
    "service": "serviceImpl",
    "jpaMetamodelFiltering": false,
    "fluentMethods": true,
    "clientRootFolder": "",
    "applications": "*"
}